{"expireTime":9007200884234947000,"key":"8c7470a2b050363cc93dafe31abbeefe","val":{"name":"IMAGE_PROCESSING","inputPaths":["C:/Users/reube/source/repos/n/team-rubot-site/src/images/tags/travel.jpg"],"outputDir":"C:/Users/reube/source/repos/n/team-rubot-site/public/static/fd92fb8e8ba793856ecd3be383c34272","args":{"isLazy":false,"operations":[{"outputPath":"86e11\\travel.jpg","args":{"width":100,"cropFocus":17,"toFormat":"jpg","fit":"cover","background":"rgba(0,0,0,1)"}},{"outputPath":"f836f\\travel.jpg","args":{"width":200,"cropFocus":17,"toFormat":"jpg","fit":"cover","background":"rgba(0,0,0,1)"}},{"outputPath":"4fe8c\\travel.jpg","args":{"width":600,"cropFocus":17,"toFormat":"jpg","fit":"cover","background":"rgba(0,0,0,1)"}},{"outputPath":"14b42\\travel.jpg","args":{"width":800,"cropFocus":17,"toFormat":"jpg","fit":"cover","background":"rgba(0,0,0,1)"}},{"outputPath":"d3bbf\\travel.jpg","args":{"width":3423,"cropFocus":17,"toFormat":"jpg","fit":"cover","background":"rgba(0,0,0,1)"}}],"pluginOptions":{"base64Width":20,"forceBase64Format":"","useMozJpeg":false,"stripMetadata":true,"lazyImageGeneration":true,"defaultQuality":50,"failOnError":true,"plugins":[]}}}}