{"expireTime":9007200883430815000,"key":"e8f230e81456fce3c03856f980a6efcc","val":{"name":"IMAGE_PROCESSING","inputPaths":["C:/Users/reube/source/repos/n/rol/content/2020-04-08-why-I-migrated-my-website-from-worpress-to-gatsby/gatsby-wordpress.jpg"],"outputDir":"C:/Users/reube/source/repos/n/rol/public/static/245aecc3e8c42b31f1e4796cebebd2ce","args":{"isLazy":false,"operations":[{"outputPath":"8f7df\\gatsby-wordpress.jpg","args":{"width":250,"cropFocus":17,"toFormat":"jpg","fit":"cover","background":"rgba(0,0,0,1)"}},{"outputPath":"0f3a1\\gatsby-wordpress.jpg","args":{"width":500,"cropFocus":17,"toFormat":"jpg","fit":"cover","background":"rgba(0,0,0,1)"}},{"outputPath":"f9913\\gatsby-wordpress.jpg","args":{"width":750,"cropFocus":17,"toFormat":"jpg","fit":"cover","background":"rgba(0,0,0,1)"}}],"pluginOptions":{"base64Width":20,"forceBase64Format":"","useMozJpeg":false,"stripMetadata":true,"lazyImageGeneration":true,"defaultQuality":50,"failOnError":true,"plugins":[]}}}}